plateypus/__init__.py
plateypus/__main__.py
plateypus/plateypusLogo.png
plateypus/dataprocessing/__init__.py
plateypus/dataprocessing/cellDataProcessing.py
plateypus/dataprocessing/cytokineDataProcessing.py
plateypus/dataprocessing/dataProcessingGUI.py
plateypus/dataprocessing/initialDataProcessing.py
plateypus/dataprocessing/killingDataProcessing.py
plateypus/dataprocessing/miscFunctions.py
plateypus/dataprocessing/pcrDataProcessing.py
plateypus/dataprocessing/proliferationDataProcessing.py
plateypus/dataprocessing/singleCellDataProcessing.py
plateypus/plotting/__init__.py
plateypus/plotting/facetPlot1D.py
plateypus/plotting/facetPlot2D.py
plateypus/plotting/facetPlot3D.py
plateypus/plotting/facetPlotCategorical.py
plateypus/plotting/facetPlotLibrary.py
plateypus/plotting/interactiveGUIElements.py
plateypus/plotting/plottingGUI.py
plateypus/setup/__init__.py
plateypus/setup/createPlateLayout.py
plateypus/setup/createTubeLayout.py
plateypus/setup/experimentCreationGUI.py
plateypus/setup/experimentSetupGUI.py
plateypus/setup/removeExperiment.py
plateypus/templates/cytokineMWDf_template.csv
plateypus/templates/kitDf_template.csv
plateypus-0.6.11.dist-info/LICENSE.txt
plateypus-0.6.11.dist-info/METADATA
plateypus-0.6.11.dist-info/WHEEL
plateypus-0.6.11.dist-info/entry_points.txt
plateypus-0.6.11.dist-info/top_level.txt
plateypus-0.6.11.dist-info/RECORD
