Metadata-Version: 2.1
Name: plateypus
Version: 0.6.11
Summary: Processes and plots high throughput cytometry experiments through a GUI
Home-page: https://github.com/soorajachar/plateypus
Author: Sooraj Achar
Author-email: acharsr@nih.gov
Classifier: Programming Language :: Python :: 3
Classifier: License :: OSI Approved :: GNU General Public License v3 (GPLv3)
Classifier: Operating System :: Unix
Classifier: Operating System :: MacOS :: MacOS X
Classifier: Operating System :: Microsoft :: Windows
Classifier: Intended Audience :: Science/Research
License-File: LICENSE.txt
Requires-Dist: matplotlib<=3.5.2
Requires-Dist: pandas<2.0.0
Requires-Dist: seaborn
Requires-Dist: scipy
Requires-Dist: openpyxl
Requires-Dist: tables
Requires-Dist: pillow<=9.5.0
Requires-Dist: colorcet
Requires-Dist: importlib-metadata
